liquidb/__init__.py
liquidb/admin.py
liquidb/apps.py
liquidb/consts.py
liquidb/db_tools.py
liquidb/models.py
liquidb/pylint_settings.py
liquidb/settings.py
liquidb/management/__init__.py
liquidb/management/commands/__init__.py
liquidb/management/commands/_private.py
liquidb/management/commands/checkout_latest_snapshot.py
liquidb/management/commands/checkout_snapshot.py
liquidb/management/commands/create_migration_snapshot.py
liquidb/management/commands/delete_snapshot_by_name.py
liquidb/management/commands/delete_snapshot_history.py
liquidb/migrations/0001_initial.py
liquidb/migrations/__init__.py
django_liquidb-0.4.dist-info/LICENSE.md
django_liquidb-0.4.dist-info/METADATA
django_liquidb-0.4.dist-info/WHEEL
django_liquidb-0.4.dist-info/top_level.txt
django_liquidb-0.4.dist-info/RECORD
