Metadata-Version: 2.1
Name: django-liquidb
Version: 0.4
Summary: Liquidb is a Django app that simplifies migration management.
Author: Vitalii Gusakovskiy
License: ## License
Project-URL: Repository, https://github.com/Gusakovskiy/django-liquidb
Project-URL: Source, https://pypi.org/project/django-liquidb/
Classifier: Development Status :: 4 - Beta
Classifier: Environment :: Web Environment
Classifier: Framework :: Django
Classifier: Intended Audience :: Developers
Classifier: Operating System :: OS Independent
Classifier: Programming Language :: Python :: 3.8
Classifier: Programming Language :: Python :: 3.9
Classifier: Programming Language :: Python :: 3.10
Classifier: Programming Language :: Python :: 3.11
Classifier: Topic :: Database
Classifier: Topic :: Internet :: WWW/HTTP
Classifier: Topic :: Internet :: WWW/HTTP :: Dynamic Content
Classifier: Topic :: Internet :: WWW/HTTP :: Dynamic Content :: CGI Tools/Libraries
Requires-Python: >=3.8
License-File: LICENSE.md
Requires-Dist: django >=3.2
Provides-Extra: dev
Requires-Dist: pylint ; extra == 'dev'
Requires-Dist: pytest ; extra == 'dev'
Requires-Dist: pytest-cov ; extra == 'dev'
Requires-Dist: pylint-django ; extra == 'dev'
Requires-Dist: mock ; extra == 'dev'
Requires-Dist: pytest-django ; extra == 'dev'
Requires-Dist: beautifulsoup4 ; extra == 'dev'
Requires-Dist: black ; extra == 'dev'
Requires-Dist: twine ; extra == 'dev'
Requires-Dist: build ; extra == 'dev'
Requires-Dist: pip-tools ; extra == 'dev'
